{
  "name": "skillswap-hub-client",
  "version": "1.0.0",
  "private": true,
  "description": "SkillSwap Hub React frontend using hooks and Fetch API.",
  "scripts": {
    "dev": "vite",
    "build": "vite build",
    "preview": "vite preview",
    "lint": "eslint .",
    "format": "prettier --write ."
  },
  "dependencies": {
    "@vitejs/plugin-react": "^4.3.1",
    "vite": "^5.4.0",
    "react": "^18.3.1",
    "react-dom": "^18.3.1",
    "prop-types": "^15.8.1"
  },
  "devDependencies": {
    "eslint": "^8.57.0",
    "eslint-plugin-react": "^7.35.0",
    "eslint-plugin-react-hooks": "^4.6.2",
    "prettier": "^3.3.3"
  }
}
